{
  "panId": "2015122300019551",
  "공고명": "2026년 신혼·신생아 전세임대Ⅱ 입주자 수시모집",
  "유형": "전세임대",
  "상품구조": "전세임대",
  "모집유형": "수시",
  "분양전환": "비분양전환형",
  "지역": "세종특별자치시 세종시",
  "공고일": "공고문미기재",
  "접수시작": "2026-03-24",
  "마감일": "2026-12-31",
  "상태": "접수중",
  "당첨자발표": "신청일로부터 최소 10주 소요(소득·자산확인 필요시), 개별 SMS·e-mail 안내",
  "접수방법": "인터넷",
  "단지": [],
  "공급형": [],
  "선정방식": "순차",
  "선정방식상세": "전국 사업대상으로 단지·면적 구분 없이 신청자격 순위(1~4순위)에 따라 입주대상자 선정. 별도 배점·추첨 규정 본문 없음(순위 충족자가 지원한도 내 전세주택을 물색하여 LH가 전세계약 체결 후 재임대).",
  "자격요건": {
    "무주택": "신청일 기준 무주택세대구성원. 세대구성원 전원이 주택을 소유하지 않아야 하며, 배우자가 세대 분리된 경우 배우자 및 배우자가 속한 주민등록표등본의 무주택세대구성원까지 포함.",
    "소득기준": {
      "종류": "도시근로자%",
      "기본퍼센트": 130,
      "가구원수별": {
        "2인": {
          "130%": 8212778,
          "200%": 12319167
        },
        "3인": {
          "130%": 10618958,
          "200%": 16336858
        },
        "4인": {
          "130%": 11442863,
          "200%": 17604404
        },
        "5인": {
          "130%": 12125081,
          "200%": 18653970
        },
        "6인": {
          "130%": 12878142,
          "200%": 19812526
        },
        "7인": {
          "130%": 13631203,
          "200%": 20971082
        },
        "8인": {
          "130%": 14384265,
          "200%": 22129638
        }
      },
      "가산규칙": "전년도 도시근로자 가구원수별 가구당 월평균소득의 130% 이하(본인과 배우자 모두 소득이 있는 경우 200% 이하). 2인가구는 10%p 가산한 금액임. 6인 이상 가구는 5인가구 소득에 1인당 평균금액(579,278원)을 합산하여 산정.",
      "비고": "월평균소득액은 세전금액으로서 해당세대 전원의 월평균소득액 합산. 가구원수는 해당세대 전원(태아 포함)."
    },
    "자산상한": 362000000,
    "자동차상한": "공고문미기재",
    "청약요건": "없음",
    "대상계층": [
      "신혼·한부모",
      "유자녀 혼인가구",
      "신생아 가구"
    ],
    "계층별": null
  },
  "순위규칙": [
    {
      "순위": 1,
      "기준": "자격유형",
      "조건": [
        "신생아 가구(신청일 기준 2년 이내 출산·입양 자녀 또는 태아 있는 가구)",
        "한부모가족지원법 시행규칙 제3조에 따라 성평등가족부장관이 정하여 고시하는 한부모가족"
      ],
      "적용면적": null
    },
    {
      "순위": 2,
      "기준": "자격유형",
      "조건": [
        "신청일 기준 미성년 자녀(태아 포함)가 있는 신혼부부·예비신혼부부",
        "신청일 기준 6세 이하 자녀(태아포함)를 둔 한부모가족"
      ],
      "적용면적": null
    },
    {
      "순위": 3,
      "기준": "자격유형",
      "조건": [
        "미성년 자녀(태아 포함)가 없는 신혼부부·예비신혼부부"
      ],
      "적용면적": null
    },
    {
      "순위": 4,
      "기준": "자격유형",
      "조건": [
        "유자녀 혼인가구(6세 이하 자녀, 1·2순위 비해당)"
      ],
      "적용면적": null
    }
  ],
  "배점표": [],
  "우선배정": [],
  "전세지원": {
    "지원한도": {
      "수도권": {
        "1인": 240000000,
        "2인": 240000000,
        "3인+": 240000000
      },
      "광역시": {
        "1인": 160000000,
        "2인": 160000000,
        "3인+": 160000000
      },
      "기타": {
        "1인": 130000000,
        "2인": 130000000,
        "3인+": 130000000
      }
    },
    "한도초과허용": "지역별 지원한도액 초과 주택은 초과 전세금액을 입주대상자가 부담하고 임차권은 LH에 귀속되는 조건으로 지원 가능. 전세금 총액은 호당 지원한도액의 250% 이내(가구원수 5인 이상은 250% 초과 가능).",
    "본인부담": "지원한도액 범위 내 전세보증금의 20% 해당액(임대보증금)",
    "금리": "월임대료 = (전세보증금-임대보증금)에 대한 연 1.2~2.2% 이자. 지원보증금 4천만원 이하 1.2%, 4천만원 초과~6천만원 이하 1.7%, 6천만원 초과 2.2%. 우대금리: 미성년 자녀 1자녀 0.2%p·2자녀 0.3%p·3자녀 0.5%p, 생계·의료급여 수급자 0.2%p(최저금리 1.2%).",
    "대상주택조건": {
      "전용면적상한": 85,
      "부채비율": "공고문미기재",
      "주택유형": [
        "단독주택",
        "다가구주택",
        "연립주택",
        "아파트",
        "주거용 오피스텔"
      ]
    },
    "지역범위": "전국. 입주대상자가 신청한 지역의 국민주택 규모(전용 85㎡) 이하 전세 또는 보증부월세 주택.",
    "거주지제한": "공고문미기재"
  },
  "매입주택": null,
  "특이사항": [
    "신혼·신생아 전세임대Ⅱ는 기존 Ⅰ보다 소득요건 완화(70%→130%, 맞벌이 90%→200%)·지원한도 상향한 유형.",
    "공급호수 1,170호(전국 단위 수시모집, 단지·면적 구분 없음).",
    "임대기간 최장 10년(2년 단위, 4회 재계약). 미성년 자녀가 있는 경우 2회 추가(최장 14년).",
    "순위별·지역별 중복 신청 불가(전부 무효). 현재 청년1순위·다자녀·신혼1 유형도 모집 중이라 중복 계약 불가.",
    "신생아가구 특례: 2024년 이후 출생 자녀가 있는 경우 해당 자녀 성년 이전까지 계속 재계약 가능.",
    "보증부월세 주택은 협의 후 전세 전환 또는 추가 보증금 납부로 지원 가능(임차료 지급보증 활용 시 3개월치만 부담).",
    "자산기준: 출생자녀수에 따라 총자산 362,000,000원(105%)~396,000,000원(+10%p)~431,000,000원(+20%p)으로 차등 적용되나 기본 신청자격 기준은 36,200만원 이하."
  ],
  "_검증노트": [
    "공고일: 본문에 명시적 공고일자 표기 없어 공고문미기재.",
    "지역: 목록기준 '세종'으로 지정되었으나 본문 사업대상지역은 '전국'. 지역범위·지원한도(광역시-세종시 포함 16,000만원)에 세종 포함됨. 시군구 표기는 세종특별자치시로 처리.",
    "자동차상한: 자동차는 총자산에 합산 검색되나 별도 자동차 가액 상한 금액 본문 미기재.",
    "단지·공급형: 전세임대 상품 특성상 특정 단지/평형 없음(입주자가 전세주택 물색). 빈 배열 처리.",
    "당첨자발표: 확정 날짜 없이 '신청일로부터 최소 10주' 문구 및 개별 안내로 기재됨.",
    "전세지원 지원한도: 가구원수별 차등 없이 권역별 단일 한도(수도권 24,000만/광역시 16,000만/기타 13,000만)이므로 1인·2인·3인+ 동일값 입력.",
    "선정방식: 본문에 배점표·추첨 규정 없이 자격순위(1~4순위)로만 선정하여 '순차'로 판단."
  ],
  "원문링크": {
    "상세페이지": "https://apply.lh.or.kr/lhapply/apply/wt/wrtanc/selectWrtancInfo.do?panId=2015122300019551",
    "공고문PDF": "https://apply.lh.or.kr/lhapply/lhFile.do?fileid=66097034",
    "로컬PDF": "/Users/snfddl/project/active/happy-house/data/raw/lh/2015122300019551/files/66097034__[공고문]2026년신혼·신생아전세임대Ⅱ입주자수시모집.pdf",
    "첨부": [
      {
        "name": "[공고문]2026년신혼·신생아전세임대Ⅱ입주자수시모집.hwpx",
        "ext": ".hwpx",
        "다운로드": "https://apply.lh.or.kr/lhapply/lhFile.do?fileid=66097030"
      },
      {
        "name": "[공고문]2026년신혼·신생아전세임대Ⅱ입주자수시모집.pdf",
        "ext": ".pdf",
        "다운로드": "https://apply.lh.or.kr/lhapply/lhFile.do?fileid=66097034"
      },
      {
        "name": "1.2026년신혼신생아전세임대ⅠㆍⅡ주요문의사항QnA.hwp",
        "ext": ".hwp",
        "다운로드": "https://apply.lh.or.kr/lhapply/lhFile.do?fileid=66097008"
      },
      {
        "name": "2-1.금융정보등(금융ㆍ신용ㆍ보험정보)제공동의서및유의사항.hwp",
        "ext": ".hwp",
        "다운로드": "https://apply.lh.or.kr/lhapply/lhFile.do?fileid=66097009"
      },
      {
        "name": "2-2.샘플_금융정보제공동의서.pdf",
        "ext": ".pdf",
        "다운로드": "https://apply.lh.or.kr/lhapply/lhFile.do?fileid=66097010"
      },
      {
        "name": "3.자산보유사실확인서및유의사항.hwp",
        "ext": ".hwp",
        "다운로드": "https://apply.lh.or.kr/lhapply/lhFile.do?fileid=66097011"
      },
      {
        "name": "4.개인정보수집이용및제3자제공동의서(양식)_전세임대.hwp",
        "ext": ".hwp",
        "다운로드": "https://apply.lh.or.kr/lhapply/lhFile.do?fileid=66097012"
      },
      {
        "name": "5.한부모가족세대구성확인서.hwp",
        "ext": ".hwp",
        "다운로드": "https://apply.lh.or.kr/lhapply/lhFile.do?fileid=66097013"
      },
      {
        "name": "6.예비신혼부부세대구성확인서.hwp",
        "ext": ".hwp",
        "다운로드": "https://apply.lh.or.kr/lhapply/lhFile.do?fileid=66097014"
      },
      {
        "name": "7.예비신혼부부전세임대신청위임장.hwp",
        "ext": ".hwp",
        "다운로드": "https://apply.lh.or.kr/lhapply/lhFile.do?fileid=66097015"
      },
      {
        "name": "8.예비신혼부부전세임대신청확인서.hwp",
        "ext": ".hwp",
        "다운로드": "https://apply.lh.or.kr/lhapply/lhFile.do?fileid=66097016"
      }
    ]
  }
}