{
  "panId": "2015122300020074",
  "공고명": "동해묵호 국민임대주택 예비입주자 상시모집 [소득 150% 완화적용]",
  "유형": "국민임대",
  "상품구조": "건설임대",
  "모집유형": "수시",
  "분양전환": "비분양전환형",
  "지역": "강원특별자치도 동해시",
  "공고일": "2026-06-08",
  "접수시작": "2026-06-23",
  "마감일": "2026-12-30",
  "상태": "정정공고중",
  "당첨자발표": "서류접수 후 자격검증 적격자에 한하여 공가발생 시 순번에 따라 개별통보(계약체결까지 최소 2~3개월 이상 소요)",
  "접수방법": "현장",
  "단지": [
    {
      "단지명": "동해묵호",
      "주소": "강원특별자치도 동해시 해맞이길 215 (묵호진동 110)",
      "건설세대수": 341
    }
  ],
  "공급형": [
    {
      "형명": "51",
      "전용면적": 51.86,
      "금회모집호수": 70,
      "임대료": [
        {
          "구분": "기본",
          "임대보증금": 21202000,
          "월임대료": 183740
        }
      ]
    },
    {
      "형명": "59",
      "전용면적": 59.88,
      "금회모집호수": 30,
      "임대료": [
        {
          "구분": "기본",
          "임대보증금": 25443000,
          "월임대료": 212020
        }
      ]
    }
  ],
  "선정방식": "추첨",
  "선정방식상세": "예비입주자 상시모집(현장접수). 접수 첫날 접수시간 이전 도착자는 추첨으로 접수순번을 결정하며, 이후는 접수순으로 예비자 명부 순번을 부여. 서류접수 후 자격검증 적격자에 한하여 최종 예비입주자로 등록되고 공가발생 시 순번에 따라 개별 계약안내. 별도 가점/배점표 없음(청약순위확인서는 청약배점 인정 시 제출).",
  "자격요건": {
    "무주택": "신청접수일 현재 무주택세대구성원(세대에 속하는 사람 전체가 무주택). 주택 또는 분양권등을 소유하지 아니할 것. 신청접수일로부터 입주 시까지 무주택세대구성원 유지 필요.",
    "소득기준": {
      "종류": "도시근로자%",
      "기본퍼센트": 70,
      "가구원수별": {
        "1인": {
          "70%": 3432027,
          "150%(완화)": 5720045
        },
        "2인": {
          "70%": 4693016,
          "150%(완화)": 8799405
        },
        "3인": {
          "70%": 5717900,
          "150%(완화)": 12252644
        },
        "4인": {
          "70%": 6161541,
          "150%(완화)": 13203303
        },
        "5인": {
          "70%": 6528890,
          "150%(완화)": 13990478
        },
        "6인": {
          "70%": 6934384,
          "150%(완화)": 14859395
        },
        "7인": {
          "70%": 7339879,
          "150%(완화)": 15728312
        },
        "8인": {
          "70%": 7745373,
          "150%(완화)": 16597229
        }
      },
      "가산규칙": "1인 가구 20%p, 2인 가구 10%p 가산. 출산자녀 2인 이상 20%p, 출산자녀 1인 10%p 가산(출산자녀는 '23.3.28. 이후 출산 미성년자녀, 최대 2자녀 인정). 표의 1인 90%, 2인 80%는 기본 70%에 가구원수 가산을 반영한 값.",
      "비고": "입주자격 완화 공고: 본래 전년도 월평균소득 70% 이하 기준을 150% 이하로 완화 적용. 완화 입주자는 「공공주택 업무처리지침」 제94조에 따라 재계약 1회 한하여 허용(소득·자산 초과시 할증 임대조건 적용 가능)."
    },
    "자산상한": 345000000,
    "자동차상한": 45420000,
    "청약요건": "청약 배점을 인정받으려는 경우 청약순위확인서 제출(필수 아님). 별도 청약통장 요건 명시 없음.",
    "대상계층": [
      "무주택세대구성원"
    ],
    "계층별": null
  },
  "순위규칙": [
    {
      "순위": 1,
      "기준": "자격유형",
      "조건": [
        "신청접수일 현재 무주택세대구성원",
        "완화된 소득기준(150% 이하) 충족",
        "총자산 345백만원 이하",
        "자동차 4,542만원 이하"
      ],
      "적용면적": null
    }
  ],
  "배점표": [],
  "우선배정": [],
  "전세지원": null,
  "매입주택": null,
  "특이사항": [
    "입주자격 완화 공고: 소득기준을 전년도 월평균소득 70% 이하에서 150% 이하로 완화 적용.",
    "예비입주자 상시모집 공고(공가 및 향후 해약 대비). 예비입주자로 선정되어도 현재 대기중 예비입주자의 후순위로 등록되며 실제 입주까지 상당시간 소요.",
    "현장접수만 가능(인터넷/모바일 청약 불가). 신청장소: 동해묵호 LH 주거행복지원센터(강원특별자치도 동해시 해맞이길 215).",
    "한세대당 1개단지 1개형에만 신청 가능, 중복신청 시 전부 무효처리.",
    "상시접수로 모집인원 충족 또는 공사여건에 따라 마감일 이전 조기마감 가능.",
    "분양전환 되지 않는 공공임대주택으로 입주자격 충족 시 최장 30년 거주 가능.",
    "최대전환 시 임대조건(별도): 51형 보증금 증액(+22,000,000) 시 43,202,000원/73,740원, 감액(-15,000,000) 시 6,202,000원/227,490원; 59형 증액(+25,000,000) 시 50,443,000원/87,020원, 감액(-19,000,000) 시 6,443,000원/267,430원. 보증금↔월임대료 전환 이율 증액 6%, 감액 3.5%(공고일 기준).",
    "대기중인 예비자수: 51형 0명, 59형 6명. 건설호수: 51형 233호, 59형 108호.",
    "공가호수는 2026.05.26 기준 확인값으로 실제와 상이할 수 있음.",
    "완화 입주자는 재계약 1회 한하여 허용(소득·자산 초과시 초과비율에 따른 할증 임대조건 적용 가능), 재계약 만료시 요건 충족 예비입주자 없는 경우 1회 추가 허용. 2회차 이상 갱신 시 본래 국민임대주택 입주자격 기준 적용."
  ],
  "_검증노트": [
    "당첨자발표일은 별도 일자 없이 '서류검토·전산검색 후 적격자에 한하여 공가 대상 순차적 개별통보' 문구로 기재되어 문구로 채움.",
    "공급형 형명은 주택형(51, 59)으로 기재. 임대료는 모집공고일 현재 기본 임대조건만 단일 구간으로 추출(계층/구간 구분 없음).",
    "소득기준 가구원수별 표는 본문 표 기준 70%(본래)와 150%(완화) 값을 함께 수록. 3인 이상 기본퍼센트는 표상 70%/150%로 표기되어 1인20%p·2인10%p 가산은 1~2인에만 적용됨.",
    "자산상한 345백만원(완화후), 자동차 4,542만원은 출산자녀 가산표 0명(기준)값. 본래(완화 전) 총자산 기준은 표에 34,500만원으로 동일 수준 기재.",
    "별도 배점표·우선배정 비율 표가 본문에 없어 빈 배열로 처리(편의시설 설치 대상은 배점 아님)."
  ],
  "원문링크": {
    "상세페이지": "https://apply.lh.or.kr/lhapply/apply/wt/wrtanc/selectWrtancInfo.do?panId=2015122300020074",
    "공고문PDF": "https://apply.lh.or.kr/lhapply/lhFile.do?fileid=67161360",
    "로컬PDF": "/Users/snfddl/project/active/happy-house/data/raw/lh/2015122300020074/files/67161360__260608동해묵호국민임대주택예비입주자입주자격완화(1단계)상시모집공고문.pdf",
    "첨부": [
      {
        "name": "260608동해묵호국민임대주택예비입주자입주자격완화(1단계)상시모집공고문.pdf",
        "ext": ".pdf",
        "다운로드": "https://apply.lh.or.kr/lhapply/lhFile.do?fileid=67161360"
      }
    ]
  },
  "source": "lh",
  "상품군": "임대"
}